{
  "updated": "2026-06-15T13:29:58.710842+00:00",
  "lastAttempt": "2026-06-15T13:29:58.710854+00:00",
  "tweets": [
    {
      "id": "https://nitter.net/gamegetnavi/status/2066505762344690103#m",
      "account": "gamegetnavi",
      "text": "🏢セブンネットショッピング\n\n✅30th CELEBRATION BOX\n✅30th CELEBRATION プレミアムデッキセット エーフィ・ブラッキー\n抽選販売を予告✨\n\n📅応募期間\n6月30日(火)15:00頃 応募開始\n\n📲販売速報👉 https://gamenv.net/tc/stores/comment-page-640/#comment-320250\n\n#ポケモンカード #ポケカ #",
      "link": "https://x.com/gamegetnavi/status/2066505762344690103#m",
      "pubDate": "Mon, 15 Jun 2026 12:59:02 GMT",
      "relevant": true
    },
    {
      "id": "https://nitter.net/Zabi_pokeka/status/2066502109672124743#m",
      "account": "Zabi_pokeka",
      "text": "6/15(月)トレカ情報 ザビニュース📺\nいいね リポスト フォロー ぜひお願いします🔥\n\n✅アビスアイ 11,000円台まで下落\n\n✅サカズキ・クザン コミパラPSA10早くも出品され始める‼️\n\n✅WCS2026記念プロモカード「パラダイスリゾート」イラスト公開される✨️",
      "link": "https://x.com/Zabi_pokeka/status/2066502109672124743#m",
      "pubDate": "Mon, 15 Jun 2026 12:44:31 GMT",
      "relevant": false
    },
    {
      "id": "https://nitter.net/Zabi_pokeka/status/2066489372242047365#m",
      "account": "Zabi_pokeka",
      "text": "本日告知or開始された抽選まとめ💁‍♂️\n\n【インフェルノX】\n✅ポケモンカードラウンジ 1BOX 6/17 23:59〆\nhttps://cloud-pass.jp/pr/f6b3529fc3dd8a6667c0e8fa1ec906df6936c58f1d9cfc6c2fd31c95415a06ea\n\n【MEGAドリームex】\n✅晴れる屋2秋葉原タワー店 1BOX 6/1718:00〆\nhttp",
      "link": "https://x.com/Zabi_pokeka/status/2066489372242047365#m",
      "pubDate": "Mon, 15 Jun 2026 11:53:54 GMT",
      "relevant": true
    },
    {
      "id": "https://nitter.net/pokecachan/status/2066482294567907526#m",
      "account": "pokecachan",
      "text": "R to @pokecachan: 📝購入履歴確認（6/14までに受け取り必要）\nhttps://7net.omni7.jp/general/static/mypage\n\n今回は発表前までに購入り歴が必要となります\n他店舗の条件は固定ポストよりご確認ください",
      "link": "https://x.com/pokecachan/status/2066482294567907526#m",
      "pubDate": "Mon, 15 Jun 2026 11:25:47 GMT",
      "relevant": false
    },
    {
      "id": "https://nitter.net/Zabi_pokeka/status/2066477306957136177#m",
      "account": "Zabi_pokeka",
      "text": "セブンネットショッピングで拡張パック「30th CELEBRATION」と「プレミアムデッキセット エーフィ・ブラッキー」抽選告知されました‼️\n\n【応募期間】\n6月30日(火)15時頃応募開始予定\n\n【応募条件】\n2025/6/1～2026/6/14の期間に、セブンネットショッピングで税抜1円以上の商品をご注文＆お受取りいただいたお客様\n\n#ポケモンカード #ポケカ",
      "link": "https://x.com/Zabi_pokeka/status/2066477306957136177#m",
      "pubDate": "Mon, 15 Jun 2026 11:05:57 GMT",
      "relevant": true
    },
    {
      "id": "https://nitter.net/pokecachan/status/2066476998973890691#m",
      "account": "pokecachan",
      "text": "【ポケカ30周年記念】\nセブンネットより『30周年記念BOX（30th CELEBRATION）』抽選の詳細が発表💡いいねで保存 \n\n❶30周年記念BOX\n❷プレミアムデッキセットエーフィ・ブラッキー\n📅抽選期間：6/30(火)15:00〜応募開始\n🎯当選発表：-\n⚠️購入履歴が必要（2025/6/1～2026/6/14に1円以上の購入履歴）",
      "link": "https://x.com/pokecachan/status/2066476998973890691#m",
      "pubDate": "Mon, 15 Jun 2026 11:04:44 GMT",
      "relevant": true
    },
    {
      "id": "https://nitter.net/bic_akiba/status/2066464137123938583#m",
      "account": "gamegetnavi",
      "text": "RT by @gamegetnavi: 🎺ご案内\n6/19(金)発売\n#ユニオンアリーナ\nブースターパック\n・「マクロス」シリーズVol.2【EX14BT】\n・無職転生~異世界行ったら本気出す~【UA54BT】\n\nは【事前抽選】での販売となります。\n\n⚠️詳細は画像または店頭にてご確認の上お申し込みください",
      "link": "https://x.com/bic_akiba/status/2066464137123938583#m",
      "pubDate": "Mon, 15 Jun 2026 10:13:37 GMT",
      "relevant": true
    },
    {
      "id": "https://nitter.net/gamegetnavi/status/2066452846367920324#m",
      "account": "gamegetnavi",
      "text": "海外に転売発覚の問屋はポケモンカードの取引停止が確定したそうです❗️",
      "link": "https://x.com/gamegetnavi/status/2066452846367920324#m",
      "pubDate": "Mon, 15 Jun 2026 09:28:46 GMT",
      "relevant": true
    },
    {
      "id": "https://nitter.net/gamegetnavi/status/2066450330649518444#m",
      "account": "gamegetnavi",
      "text": "トイザらス\n\n✅アビスアイ\n本日も販売中✨\n\n各店舗の転売対策が導入された影響でかなり平和になりました😊\n\n#ポケモンカード #ポケカ #トイザらス",
      "link": "https://x.com/gamegetnavi/status/2066450330649518444#m",
      "pubDate": "Mon, 15 Jun 2026 09:18:46 GMT",
      "relevant": true
    },
    {
      "id": "https://nitter.net/pokecachan/status/2066446483784904987#m",
      "account": "pokecachan",
      "text": "R to @pokecachan: 本日より抽選が開始しています",
      "link": "https://x.com/pokecachan/status/2066446483784904987#m",
      "pubDate": "Mon, 15 Jun 2026 09:03:29 GMT",
      "relevant": true
    },
    {
      "id": "https://nitter.net/gamegetnavi/status/2066443846016454669#m",
      "account": "gamegetnavi",
      "text": "コンビニ店頭 ポケカ新弾 販売速報❗\n\n🏢ローソン\n\n✅メガドリーム\n本日から当選店舗にて入荷、販売開始❗\n\n📲販売速報👉 https://gamenv.net/tc/ninja_seven/\n\n#ポケモンカード #コンビニ",
      "link": "https://x.com/gamegetnavi/status/2066443846016454669#m",
      "pubDate": "Mon, 15 Jun 2026 08:53:00 GMT",
      "relevant": true
    },
    {
      "id": "https://nitter.net/gamegetnavi/status/2066382008524415125#m",
      "account": "gamegetnavi",
      "text": "ビックカメラ ワンピースカード販売❗\n\n🏢アキバ\n\n✅ワンピカードBOX\n🔖決戦の刻OP-16\n平和に販売中✨\n\n販売速報👉http://gamenv.net/tc/biccamera/\n\n#ワンピカード #ワンピース #ワンピースカード #ビックカメラ 秋葉原",
      "link": "https://x.com/gamegetnavi/status/2066382008524415125#m",
      "pubDate": "Mon, 15 Jun 2026 04:47:17 GMT",
      "relevant": true
    },
    {
      "id": "https://nitter.net/gamegetnavi/status/2066363995641282920#m",
      "account": "gamegetnavi",
      "text": "ビックカメラ ポケカBOX抽選販売✨\n\n🏢池袋本店&池袋西口\n\nスタートデッキ100\n✅バトルコレクション\n\n📅抽選受付\n6月16日(火)〜6月18日(木）\n\n🎯当選発表\n6月20日(土)\n\n🛒購入期限\n6月21日(日)～6月22日(月)\n\n📲詳細など👉 https://gamenv.net/tc/biccamera/comment-page-165/#comment-320041\n\n#ポケモンカ",
      "link": "https://x.com/gamegetnavi/status/2066363995641282920#m",
      "pubDate": "Mon, 15 Jun 2026 03:35:42 GMT",
      "relevant": true
    },
    {
      "id": "https://nitter.net/Zabi_pokeka/status/2066362863179178199#m",
      "account": "Zabi_pokeka",
      "text": "ポケモンカードラウンジで拡張パック「インフェルノX」の抽選開始されました‼️\n\n【受付期間】\n6月17日(水)23時59分〆\n\n【当選発表】\n6月26日(金)18時頃\n\n【購入期間】\n7月3日(金)～7月10日(金)\n\n抽選ページはコチラ⬇️\nhttps://cloud-pass.jp/pr/f6b3529fc3dd8a6667c0e8fa1ec906df6936c58f1d9cfc6c2fd31",
      "link": "https://x.com/Zabi_pokeka/status/2066362863179178199#m",
      "pubDate": "Mon, 15 Jun 2026 03:31:12 GMT",
      "relevant": true
    },
    {
      "id": "https://nitter.net/gamegetnavi/status/2066362308583202920#m",
      "account": "gamegetnavi",
      "text": "しまむら ポケカ抽選結果発表📨\n\n当選結果の通知が配信開始✨\n\nご応募された方に幸があります様に🙏\n\n✅インフェルノX\n✅アビスアイ\n\n#ポケカ #ポケモンカード #しまむら",
      "link": "https://x.com/gamegetnavi/status/2066362308583202920#m",
      "pubDate": "Mon, 15 Jun 2026 03:29:00 GMT",
      "relevant": true
    },
    {
      "id": "https://nitter.net/gamegetnavi/status/2066357527378317588#m",
      "account": "gamegetnavi",
      "text": "しまむら ポケカ抽選結果発表📨\n\n当選結果の通知が配信開始✨\n\nご応募された方に幸があります様に🙏\n\n✅神の島の冒険\n✅受け継がれる意志\n✅THE BEST2 ベスト２\n\n#ポケカ #ポケモンカード #しまむら",
      "link": "https://x.com/gamegetnavi/status/2066357527378317588#m",
      "pubDate": "Mon, 15 Jun 2026 03:10:00 GMT",
      "relevant": true
    },
    {
      "id": "https://nitter.net/pokecachan/status/2066356854192836781#m",
      "account": "pokecachan",
      "text": "R to @pokecachan: ※当落の結果は、6/27販売開始日までにメールがくるようです",
      "link": "https://x.com/pokecachan/status/2066356854192836781#m",
      "pubDate": "Mon, 15 Jun 2026 03:07:19 GMT",
      "relevant": true
    },
    {
      "id": "https://nitter.net/gamegetnavi/status/2066356772449731054#m",
      "account": "gamegetnavi",
      "text": "ビックカメラ ポケカBOX抽選受付締め切り迫る⌛\n\n🏢なんば\n✅アビスアイ\n✅スタートデッキ100\n\n📅抽選受付\n6月14日(日)～6月15日(月)\n\n🎯当選発表\n6月27日(土)\n\n🛒購入期限\n6月28日(日)～6月29日(月)\n\n📲販売速報👉https://gamenv.net/tc/biccamera/comment-page-161/#comment-318066\n\n#ポケモンカード #ビ",
      "link": "https://x.com/gamegetnavi/status/2066356772449731054#m",
      "pubDate": "Mon, 15 Jun 2026 03:07:00 GMT",
      "relevant": true
    },
    {
      "id": "https://nitter.net/gamegetnavi/status/2066356269699768671#m",
      "account": "gamegetnavi",
      "text": "RT by @gamegetnavi: ポケモンカード30周年\n30th CELEBRATION『カードセット』\n\n🏢Amazon\n第2回目の当選通知あり🎯\n\n9種類の当選確認を👇\n\n✅フシギダネ・ヒトカゲ・ゼニガメ\nhttps://amazon.co.jp/dp/B0GXCYMRGL?aod=1&m=AN1VRQENFRJN5&f_freeShipping=1&linkCode=sl1&tag=",
      "link": "https://x.com/gamegetnavi/status/2066356269699768671#m",
      "pubDate": "Mon, 15 Jun 2026 03:05:00 GMT",
      "relevant": true
    },
    {
      "id": "https://nitter.net/gamegetnavi/status/2066348697403916290#m",
      "account": "gamegetnavi",
      "text": "ビックカメラ ポケモンカードBOX抽選販売✨\n\n🏢有楽町\n\n✅アビスアイ\n✅スタートデッキ100\n\n📅応募期間\n6月15日(月)〜6月18日(木)\n\n🎯当選発表\n6月19日(金)\n\n📅購入期間\n6月20日(土)～6月28日(日)\n\n販売速報⏩https://gamenv.net/tc/biccamera/comment-page-164/#comment-320006\n\n#ポケカ #ビックカメラ",
      "link": "https://x.com/gamegetnavi/status/2066348697403916290#m",
      "pubDate": "Mon, 15 Jun 2026 02:34:55 GMT",
      "relevant": true
    },
    {
      "id": "https://nitter.net/gamegetnavi/status/2066347461589823984#m",
      "account": "gamegetnavi",
      "text": "【コンビニ アビスアイ販売 情報✨】\n\n✅ファミリーマート\n✅セブンイレブン\n\n本日も入荷販売中の店舗あり🚚\n\n#コンビニ #ポケカ セブンイレブン ファミマ",
      "link": "https://x.com/gamegetnavi/status/2066347461589823984#m",
      "pubDate": "Mon, 15 Jun 2026 02:30:00 GMT",
      "relevant": true
    },
    {
      "id": "https://nitter.net/gamegetnavi/status/2066346685941551125#m",
      "account": "gamegetnavi",
      "text": "RT by @gamegetnavi: ポケモンカード30周年\n30th CELEBRATION『プレミアムデッキセット エーフィ／ブラッキー』\n\n🏢Amazon\n第2回目の当選通知あり🎯\n\n当選確認を👇\n\n⏩エーフィ／ブラッキー デッキ\nhttps://amazon.co.jp/dp/B0GXCM4BCZ?m=AN1VRQENFRJN&aod=1&tag=coras-22\n\n#ポケモン #ポケモ",
      "link": "https://x.com/gamegetnavi/status/2066346685941551125#m",
      "pubDate": "Mon, 15 Jun 2026 02:26:55 GMT",
      "relevant": true
    },
    {
      "id": "https://nitter.net/gamegetnavi/status/2066339344923902381#m",
      "account": "gamegetnavi",
      "text": "ポケカラウンジ ポケカ抽選受付開始✨\n\n✅インフェルノX\n\n📲応募期間\n6月15日(月)〜6月17日(水)\n\n🎯当選発表\n6月26日(金) 18時以降順次\n\n🛒購入期間\n7月3日(金)～7月10日(金)\n\n✅申込URL👉 https://cloud-pass.jp/pr/f6b3529fc3dd8a6667c0e8fa1ec906df6936c58f1d9cfc6c2fd31c95415a06ea",
      "link": "https://x.com/gamegetnavi/status/2066339344923902381#m",
      "pubDate": "Mon, 15 Jun 2026 01:57:45 GMT",
      "relevant": true
    },
    {
      "id": "https://nitter.net/pokecachan/status/2066324816240787638#m",
      "account": "pokecachan",
      "text": "【ポケカ大量抽選】楽天ブックス「スタートデッキ100」5個など抽選が開始💡\n📅抽選期間：6/15 10:00～ 6/18 09:59\n🛒販売期間：6/27 10:00～ 6/30 09:59\n\n✅アビスアイ\nhttp://msm.to/IVv7LB3\n✅スタートデッキ100 5個セット\nhttp://msm.to/FDc8zGk\n✅インフェルノX\nhttp://msm.to/ERev0x\n✅ニンジ",
      "link": "https://x.com/pokecachan/status/2066324816240787638#m",
      "pubDate": "Mon, 15 Jun 2026 01:00:01 GMT",
      "relevant": true
    },
    {
      "id": "https://nitter.net/gamegetnavi/status/2066324816412737756#m",
      "account": "gamegetnavi",
      "text": "RT by @gamegetnavi: 楽天ブックス 人気ポケカ抽選受付開始✨ #AD\n\n📅応募期間\n6/15～6/18 9:59\n\n🛒販売期間\n6/27 10:00 - 6/30 9:59\n\n✅アビスアイ\nhttps://a.r10.to/hY9beD\n✅スタートデッキ100 バトルコレクション 5個セット\nhttps://a.r10.to/hgEnsj\n✅ハイクラスパック MEGAドリームex",
      "link": "https://x.com/gamegetnavi/status/2066324816412737756#m",
      "pubDate": "Mon, 15 Jun 2026 01:00:01 GMT",
      "relevant": true
    },
    {
      "id": "https://nitter.net/pokecachan/status/2066289048113820001#m",
      "account": "pokecachan",
      "text": "新プロモカードが公開\n①WCS2026記念「パラダイスリゾート」\n②世界大会中のXPで参加者に配布される「レックウザ」ポケモンXPプロモ",
      "link": "https://x.com/pokecachan/status/2066289048113820001#m",
      "pubDate": "Sun, 14 Jun 2026 22:37:53 GMT",
      "relevant": false
    },
    {
      "id": "https://nitter.net/gamegetnavi/status/2066279757856293248#m",
      "account": "gamegetnavi",
      "text": "RT by @gamegetnavi: 楽天ブックス 人気ポケカ抽選 本日から抽選✨ #AD\n\n📅抽選期間\n6/15 10:00 - 6/18 9:59\n\n🛒販売期間\n6/27 10:00 - 6/30 9:59\n\n✅アビスアイ\nhttp://a.r10.to/hY9beD\n✅スタートデッキ100 バトルコレクション 5個セット\nhttp://a.r10.to/hgEnsj\n✅ハイクラスパック M",
      "link": "https://x.com/gamegetnavi/status/2066279757856293248#m",
      "pubDate": "Sun, 14 Jun 2026 22:00:58 GMT",
      "relevant": true
    },
    {
      "id": "https://nitter.net/pokecachan/status/2066278528291868982#m",
      "account": "pokecachan",
      "text": "R to @pokecachan: 本日10時から開始します",
      "link": "https://x.com/pokecachan/status/2066278528291868982#m",
      "pubDate": "Sun, 14 Jun 2026 21:56:05 GMT",
      "relevant": false
    },
    {
      "id": "https://nitter.net/Zabi_pokeka/status/2066140379075014743#m",
      "account": "Zabi_pokeka",
      "text": "6/14(日)トレカ情報 ザビニュース📺\nいいね リポスト フォロー ぜひお願いします🔥\n\n✅コダックAR PSA10 価格下がらず22,000円前後の取引で安定‼️\n\n✅メガダークライex SAR 良個体 再販の影響もありじわじわ下がる\n\n✅スタデ100バトルコレクション 2,700円台まで落ちる",
      "link": "https://x.com/Zabi_pokeka/status/2066140379075014743#m",
      "pubDate": "Sun, 14 Jun 2026 12:47:08 GMT",
      "relevant": false
    },
    {
      "id": "https://nitter.net/Zabi_pokeka/status/2066125380680077386#m",
      "account": "Zabi_pokeka",
      "text": "週末なので現在抽選中をまとめました💁‍♂️\n\n【インフェルノX】\n✅ドラスタ通販 1BOX 6/14(日)23:59〆\nhttps://dorasuta.membercard.jp/lottery\n\n【MEGAドリームex】\n晴れる屋2通販 1BOX 6/15(月)15:00〆\nhttps://docs.google.com/forms/d/e/1FAIpQLSd4IGNYOt1fKDGjRrn9",
      "link": "https://x.com/Zabi_pokeka/status/2066125380680077386#m",
      "pubDate": "Sun, 14 Jun 2026 11:47:32 GMT",
      "relevant": true
    },
    {
      "id": "https://nitter.net/pokecachan/status/2066069770248782320#m",
      "account": "pokecachan",
      "text": "【ポケカ大量抽選】明日より楽天ブックス「スタートデッキ100」5個など抽選が開始します💡開始後お知らせ📢\n📅抽選期間：6/15 10:00～ 6/18 09:59\n\n✅アビスアイ\nhttp://msm.to/IVv7LB3\n✅スタートデッキ100 5個セット\nhttp://msm.to/FDc8zGk\n✅インフェルノX\nhttp://msm.to/ERev0x\n✅ニンジャスピナー\nhttp://m",
      "link": "https://x.com/pokecachan/status/2066069770248782320#m",
      "pubDate": "Sun, 14 Jun 2026 08:06:33 GMT",
      "relevant": true
    },
    {
      "id": "https://nitter.net/pokecachan/status/2065947797812396314#m",
      "account": "pokecachan",
      "text": "R to @pokecachan: ⚠️また何回か当選結果が出ると思いますのでお知らせします\n今後の抽選も随時お知らせしていきます‼️",
      "link": "https://x.com/pokecachan/status/2065947797812396314#m",
      "pubDate": "Sun, 14 Jun 2026 00:01:53 GMT",
      "relevant": true
    },
    {
      "id": "https://nitter.net/pokecachan/status/2065917336784388192#m",
      "account": "pokecachan",
      "text": "Amazon『カードセット』『プレミアムデッキセット』2回目の当選結果が出ています💡\n招待制について画像でまとめています！商品ページorメールをご確認ください！\n\n❶30周年記念BOX\nhttps://amzn.to/4vuZo7x\n❷エーフィ&ブラッキー プレミアムデッキセット\nhttps://amzn.to/4dXYc6V\n❸カードセット9種類まとめ\nhttps://amzn.to/3PMSB",
      "link": "https://x.com/pokecachan/status/2065917336784388192#m",
      "pubDate": "Sat, 13 Jun 2026 22:00:50 GMT",
      "relevant": true
    },
    {
      "id": "https://nitter.net/Zabi_pokeka/status/2065801061693259940#m",
      "account": "Zabi_pokeka",
      "text": "一日中忙しくてトレカニュース作ることができなかったので本日はお休みになります🙇‍♂️🙇‍♂️🙇‍♂️",
      "link": "https://x.com/Zabi_pokeka/status/2065801061693259940#m",
      "pubDate": "Sat, 13 Jun 2026 14:18:48 GMT",
      "relevant": false
    },
    {
      "id": "https://nitter.net/pokecachan/status/2065722158605836684#m",
      "account": "pokecachan",
      "text": "R to @pokecachan: 本日6/13(土)開始分はなし\n\nドラゴンスター（通販）拡張パック「インフェルノX」\n📅抽選期間：6月12日22:00〜6月14日23:59\nhttps://dorasuta.membercard.jp/lottery\n\nヤマシロヤ（通販）「アビスアイ」\n📅6月12日（金）21:30 〜 6月14日（日）21:30\nhttps://docs.google.com",
      "link": "https://x.com/pokecachan/status/2065722158605836684#m",
      "pubDate": "Sat, 13 Jun 2026 09:05:16 GMT",
      "relevant": true
    },
    {
      "id": "https://nitter.net/Zabi_pokeka/status/2065422855865835549#m",
      "account": "Zabi_pokeka",
      "text": "ドラスタ通販で拡張パック「インフェルノX」の抽選開始されました🔥🔥🔥\n\n【受付期間】\n6月14日(日)23時59分〆\n\n【当選発表】\n6月15日(月)\n\n抽選ページはこちら⬇️\nhttps://dorasuta.membercard.jp/lottery",
      "link": "https://x.com/Zabi_pokeka/status/2065422855865835549#m",
      "pubDate": "Fri, 12 Jun 2026 13:15:57 GMT",
      "relevant": true
    },
    {
      "id": "https://nitter.net/Zabi_pokeka/status/2065421582420619357#m",
      "account": "Zabi_pokeka",
      "text": "6/12(金)トレカ情報 ザビニュース📺\nいいね リポスト フォロー ぜひお願いします🔥\n\n✅マックピカチュウPSA10鑑定枚数 270,000枚突破する‼️\n\n✅ニカ コミパラPSA10 1,600,000円でも取引され始める📈\n\n✅スタデ100バトルコレクション未開封 2,800円台の取引とじわじわ下がる",
      "link": "https://x.com/Zabi_pokeka/status/2065421582420619357#m",
      "pubDate": "Fri, 12 Jun 2026 13:10:53 GMT",
      "relevant": false
    },
    {
      "id": "https://nitter.net/pokecachan/status/2065420446070436239#m",
      "account": "pokecachan",
      "text": "ドラゴンスター（通販）拡張パック「インフェルノX」抽選開始\n📅抽選期間：6月12日22:00〜6月14日23:59\n🎯当選発表：6月15日\nhttps://dorasuta.membercard.jp/lottery",
      "link": "https://x.com/pokecachan/status/2065420446070436239#m",
      "pubDate": "Fri, 12 Jun 2026 13:06:22 GMT",
      "relevant": true
    },
    {
      "id": "https://nitter.net/pokecachan/status/2065411742671483165#m",
      "account": "pokecachan",
      "text": "R to @pokecachan: ヤマシロヤ「アビスアイ」抽選開始\n📅6月12日（金）21:30 〜 6月14日（日）21:30\nhttps://docs.google.com/forms/d/e/1FAIpQLSfJkwxR-rgOvz2LiXj1MSsTCwSIi-C4x0a0XdML8NIMUMpX5g/viewform",
      "link": "https://x.com/pokecachan/status/2065411742671483165#m",
      "pubDate": "Fri, 12 Jun 2026 12:31:47 GMT",
      "relevant": true
    },
    {
      "id": "https://nitter.net/Zabi_pokeka/status/2065374668677382261#m",
      "account": "Zabi_pokeka",
      "text": "本日21時30分からヤマシロヤで拡張パック「アビスアイ」の抽選開始されます‼️\n\n【受付期間】\n6月12日(金)21時30分～6月14日(日)21時30分〆\n\n【当選発表】\n6月18日(木)\n\n抽選ページはこちら⬇️\nhttps://docs.google.com/forms/d/e/1FAIpQLSfJkwxR-rgOvz2LiXj1MSsTCwSIi-C4x0a0XdML8NIMUMpX5g/",
      "link": "https://x.com/Zabi_pokeka/status/2065374668677382261#m",
      "pubDate": "Fri, 12 Jun 2026 10:04:28 GMT",
      "relevant": true
    },
    {
      "id": "https://nitter.net/pokecachan/status/2065374406017470556#m",
      "account": "pokecachan",
      "text": "ヤマシロヤ（通販）「アビスアイ」再販分の抽選が21時から開始\n\n✅応募期間：6/12(金) 21:30〜 6/14(日)21:30 \n🎯当選発表：6/18(木)\nhttps://docs.google.com/forms/d/e/1FAIpQLSfJkwxR-rgOvz2LiXj1MSsTCwSIi-C4x0a0XdML8NIMUMpX5g/viewform?usp=dialog",
      "link": "https://x.com/pokecachan/status/2065374406017470556#m",
      "pubDate": "Fri, 12 Jun 2026 10:03:25 GMT",
      "relevant": true
    },
    {
      "id": "https://nitter.net/pokecachan/status/2065344448062464356#m",
      "account": "pokecachan",
      "text": "ポケモンカード抽選まとめ【6/12(金)更新】\nポケカ30周年記念BOXの抽選発表が0件、再販分が3件追加\n\n✅Amazon（通販）❷❸は昨日1回目の当選通知あり\n招待リクエスト後に当選で予約可能\n❶30周年記念BOX\nhttps://amzn.to/4vuZo7x\n❷エーフィ&ブラッキー プレミアムデッキセット\nhttps://amzn.to/4dXYc6V\n❸カードセット9種類まとめ\nhttp",
      "link": "https://x.com/pokecachan/status/2065344448062464356#m",
      "pubDate": "Fri, 12 Jun 2026 08:04:23 GMT",
      "relevant": true
    },
    {
      "id": "https://nitter.net/Zabi_pokeka/status/2065318822131749281#m",
      "account": "Zabi_pokeka",
      "text": "楽天ブックスで「インフェルノX/アビスアイ/MEGAドリームex」などの抽選告知されました‼️\n\n【受付期間】\n6月15日(月)10時～6月18日(木)9時59分\n\n【当選発表】\n6月27日(土)までに発表\n\n🛒購入期間\n6月27日(土)10時～6月30日(火)9時59分\n\nページはこちら⬇️\n・アビスアイ\nhttps://books.rakuten.co.jp/rb/18537075/?bkts",
      "link": "https://x.com/Zabi_pokeka/status/2065318822131749281#m",
      "pubDate": "Fri, 12 Jun 2026 06:22:33 GMT",
      "relevant": true
    },
    {
      "id": "https://nitter.net/pokecachan/status/2065316717098848481#m",
      "account": "pokecachan",
      "text": "R to @pokecachan: 追加\n✅ムニキスゼロ\nhttp://msm.to/58EmoMk\n\n#PR",
      "link": "https://x.com/pokecachan/status/2065316717098848481#m",
      "pubDate": "Fri, 12 Jun 2026 06:14:11 GMT",
      "relevant": false
    },
    {
      "id": "https://nitter.net/pokecachan/status/2065315277500502402#m",
      "account": "pokecachan",
      "text": "【ポケカ大量抽選】楽天ブックス「スタートデッキ100」5個など抽選が開始します💡開始後お知らせ📢\n\n📅抽選期間：6/15 10:00～ 6/18 09:59\n🛒販売期間：6/27 10:00～ 6/30 09:59\n✅アビスアイ\nhttp://msm.to/IVv7LB3\n✅スタートデッキ100 バトルコレクション 5個セット\nhttp://msm.to/FDc8zGk\n✅インフェルノX\nhttp",
      "link": "https://x.com/pokecachan/status/2065315277500502402#m",
      "pubDate": "Fri, 12 Jun 2026 06:08:28 GMT",
      "relevant": true
    },
    {
      "id": "https://nitter.net/Zabi_pokeka/status/2065300425394508175#m",
      "account": "Zabi_pokeka",
      "text": "『ポケットモンスター』シリーズの歴代ゲームソフトのパッケージがデザインされたグッズがポケモンセンターオンラインに登場‼️\n\n【発売日】\n6月18日(木)10時～\n\nやっとパッケージピンズ発売される🥰🥰🥰\n\n詳細はコチラ⬇️\nhttps://www.pokemon.co.jp/goods/2026/06/260612_go01.html",
      "link": "https://x.com/Zabi_pokeka/status/2065300425394508175#m",
      "pubDate": "Fri, 12 Jun 2026 05:09:27 GMT",
      "relevant": false
    },
    {
      "id": "https://nitter.net/pokecachan/status/2065267490352193802#m",
      "account": "pokecachan",
      "text": "あみあみ「スタートデッキ100」先着\nhttps://www.amiami.jp/top/detail/detail?gcode=CARD-00030867",
      "link": "https://x.com/pokecachan/status/2065267490352193802#m",
      "pubDate": "Fri, 12 Jun 2026 02:58:35 GMT",
      "relevant": false
    },
    {
      "id": "https://nitter.net/pokecachan/status/2065193118425858554#m",
      "account": "pokecachan",
      "text": "R to @pokecachan: 発売日まで何回も当選通知が出てきますのでまたお知らせします📣",
      "link": "https://x.com/pokecachan/status/2065193118425858554#m",
      "pubDate": "Thu, 11 Jun 2026 22:03:03 GMT",
      "relevant": true
    },
    {
      "id": "https://nitter.net/Zabi_pokeka/status/2065082685727584716#m",
      "account": "Zabi_pokeka",
      "text": "スタートデッキ100バトルコレクション発売から約半年経ち再販も結構されていますが全然価格下がらない😌\n\nリーリエのピッピex SAR 100,000円\n\nピカチュウex SAR 340,000円\n\nイーブイAR 100,000円\n\nメガリザードンY ex MUR 1,300,000円",
      "link": "https://x.com/Zabi_pokeka/status/2065082685727584716#m",
      "pubDate": "Thu, 11 Jun 2026 14:44:14 GMT",
      "relevant": false
    },
    {
      "id": "https://nitter.net/Zabi_pokeka/status/2065057866147639597#m",
      "account": "Zabi_pokeka",
      "text": "6/11(木)トレカ情報 ザビニュース📺\nいいね リポスト フォロー ぜひお願いします🔥\n\n✅ピカチュウex SAR PSA10 100,000円台復帰‼️\n\n✅メガリザードンY ex MUR 素体 スタデ再販続いてもなかなか下がらない\n\n✅新時代の主役 57,000円台まで高騰中📈",
      "link": "https://x.com/Zabi_pokeka/status/2065057866147639597#m",
      "pubDate": "Thu, 11 Jun 2026 13:05:36 GMT",
      "relevant": false
    },
    {
      "id": "https://nitter.net/pokecachan/status/2065021295671308683#m",
      "account": "pokecachan",
      "text": "R to @pokecachan: ・購入期限は当選後48時間いないとなっています\n\n・招待リクエストは12か月間有効\n・一度リクエストすれば再申請不要\n⚠️また何回か当選結果が出ると思いますのでお知らせします📣",
      "link": "https://x.com/pokecachan/status/2065021295671308683#m",
      "pubDate": "Thu, 11 Jun 2026 10:40:17 GMT",
      "relevant": true
    },
    {
      "id": "https://nitter.net/pokecachan/status/2065002646499733851#m",
      "account": "pokecachan",
      "text": "【速報】Amazonポケカ30周年『カードセット』『エーフィ&ブラッキー』当選結果がでています💡リンクからカートに入るかご確認ください！招待制についてもまとめおきます📝\n\n✅エーフィ・ブラッキー30th CELEBRATIONプレミアムデッキセット\nhttps://amzn.to/4etxK5g\n\n✅カードセット\n❶赤緑世代：フシギダネ・ヒトカゲ・ゼニガメ\nhttps://amzn.to/3RMY",
      "link": "https://x.com/pokecachan/status/2065002646499733851#m",
      "pubDate": "Thu, 11 Jun 2026 09:26:11 GMT",
      "relevant": true
    },
    {
      "id": "https://nitter.net/Zabi_pokeka/status/2064987597206864190#m",
      "account": "Zabi_pokeka",
      "text": "ONE PIECEカードゲーム公式ショップで「ブースターパック 決戦の刻【OP-16】」の抽選開始されました‼️\n\n【受付期間】\n6月15日(月) 23時59分〆\n\n【当選発表】\n6月16日(火) 17時\n\n【販売期間】\n6月20日(土)～6月21日(日)\n\n応募ページはこちら⬇️\nhttps://parks2.bandainamco-am.co.jp/category/ECCL00000043/",
      "link": "https://x.com/Zabi_pokeka/status/2064987597206864190#m",
      "pubDate": "Thu, 11 Jun 2026 08:26:23 GMT",
      "relevant": true
    },
    {
      "id": "https://nitter.net/Zabi_pokeka/status/2064729008160546839#m",
      "account": "Zabi_pokeka",
      "text": "先程Joshinアプリで拡張パック「アビスアイ」の抽選開始されたので寝る前に応募しておきましょう🙆‍♂️\n\n【受付期間】\n6月14日(日)23:59〆\n\n【当選発表】\n6月19日(金)15:00頃\n\nJoshinアプリから応募\n※シルバースマイル会員以上が対象",
      "link": "https://x.com/Zabi_pokeka/status/2064729008160546839#m",
      "pubDate": "Wed, 10 Jun 2026 15:18:51 GMT",
      "relevant": true
    },
    {
      "id": "https://nitter.net/Zabi_pokeka/status/2064693439040831691#m",
      "account": "Zabi_pokeka",
      "text": "6/10(水)トレカ情報 ザビニュース📺\nいいね リポスト フォロー ぜひお願いします🔥\n\n✅ピカチュウex SAR PSA10 価格下がるが取引活発の状況続く‼️\n\n✅スタートデッキ ルフィ&エース 27,000円台まで上昇中📈\n\n✅ジャンプ ルフィ プロモ PSA10 110,000円台まで高騰中📈",
      "link": "https://x.com/Zabi_pokeka/status/2064693439040831691#m",
      "pubDate": "Wed, 10 Jun 2026 12:57:30 GMT",
      "relevant": false
    },
    {
      "id": "https://nitter.net/Zabi_pokeka/status/2064663846997123424#m",
      "account": "Zabi_pokeka",
      "text": "本日告知or開始された抽選まとめ💁‍♂️\n\n【30th CELEBRATION】\n✅ノジマオンライン \nhttps://docs.google.com/forms/d/e/1FAIpQLSe2tm0oG-L8fBGGdkqdWNJD2NRkl7IHSWxGKKcFoU_u0-K1Ow/viewform\n\n【アビスアイ】\n✅フルコンプ 6/14(日)11:59〆\nhttps://livepocket",
      "link": "https://x.com/Zabi_pokeka/status/2064663846997123424#m",
      "pubDate": "Wed, 10 Jun 2026 10:59:55 GMT",
      "relevant": true
    },
    {
      "id": "https://nitter.net/Zabi_pokeka/status/2064571299234730005#m",
      "account": "Zabi_pokeka",
      "text": "ノジマオンラインで「30th CELEBRATION」の抽選開始されました‼️\n\n【当選発表】\n不定期でメールにてご案内\n\n抽選ページはこちら⬇️\nhttps://docs.google.com/forms/d/e/1FAIpQLSe2tm0oG-L8fBGGdkqdWNJD2NRkl7IHSWxGKKcFoU_u0-K1Ow/viewform",
      "link": "https://x.com/Zabi_pokeka/status/2064571299234730005#m",
      "pubDate": "Wed, 10 Jun 2026 04:52:10 GMT",
      "relevant": true
    },
    {
      "id": "https://nitter.net/Zabi_pokeka/status/2064361553101824146#m",
      "account": "Zabi_pokeka",
      "text": "ポケモンカード スケジュール 更新✨\n\n7月31日(金)\n「ストームエメラルダ」\n\n9月16日(水)\n「30th CELEBRATION」\n「30th プレミアムデッキセット エーフィ＆ブラッキー」\n「30th CELEBRATION Futuristic BOX」\n\n10月16日(金)発売\n30th CELEBRATION カードセット\nカントー地方～パルデア地方まで全9種類発売\n\n11月27日",
      "link": "https://x.com/Zabi_pokeka/status/2064361553101824146#m",
      "pubDate": "Tue, 09 Jun 2026 14:58:42 GMT",
      "relevant": true
    }
  ],
  "log": [
    "pokecachan: OK (https://nitter.net) - 21件",
    "Zabi_pokeka: OK (https://nitter.net) - 20件",
    "gamegetnavi: OK (https://nitter.net) - 17件"
  ]
}